{"number":1016,"state":"open","title":"\"Move\" privilege allows comment reset of other users","body":"In addition to the ability to move users into other channels, the \"Move\" privilege also allows any user with this privilege enabled to reset/erase the comments of other users.\r\n\r\nThis seems to be a bug, as there is no indication that this extra ability is granted with this privilege.\n\n\n*This ticket has been migrated from sourceforge. It is thus missing some details like original creator etc.\nThe original is at https://sourceforge.net/p/mumble/bugs/1016/ .","user":{"email":"selilyse@users.sourceforge.net"},"labels":[{"name":"privilege"}],"created_at":"2013-07-19T00:22:53.891Z","updated_at":"2013-07-19T00:22:54.427Z"}
