{"number":1018,"state":"open","title":"mumble hangs on start up","body":"Whenever I launch mumble it hangs, unresponsive, until I shut it down using Task Manager. I have tried reinstalling and using compatibility mode but it doesn't help. The closest I got to making it work was with 1.2.3's backward compatibility mode, but even then i couldn't connect to any servers.\r\n\r\nmy specs are:\r\nIntel(R) Core(TM) i5-2500K CPU @ 3.30GHz\r\n8.00 GB RAM\r\n64 bit\n\n\n*This ticket has been migrated from sourceforge. It is thus missing some details like original creator etc.\nThe original is at https://sourceforge.net/p/mumble/bugs/1018/ .*","user":{"email":"thegummster@users.sourceforge.net"},"created_at":"2013-07-23T18:41:50.174Z","updated_at":"2013-08-16T13:41:03.484Z"}
